primeutility/__init__.py
primeutility-1.0.dist-info/LICENSE
primeutility-1.0.dist-info/METADATA
primeutility-1.0.dist-info/WHEEL
primeutility-1.0.dist-info/top_level.txt
primeutility-1.0.dist-info/RECORD
