Metadata-Version: 2.1
Name: primeutility
Version: 1.0
Summary: A tool to find and list the prime numbers between one and n (user input)
Home-page: UNKNOWN
Author: Santiago Movilla
Author-email: s.movilla82@gmail.com
License: GNU GPLv3
Keywords: pyprimeutulity mathematical prime
Platform: UNKNOWN
Classifier: Development Status :: 4 - Beta
Classifier: Intended Audience :: Developers
Classifier: Topic :: Utilities
Classifier: License :: OSI Approved :: GNU General Public License v3 (GPLv3)
Classifier: Programming Language :: Python :: 3
Classifier: Operating System :: OS Independent
License-File: LICENSE
